encryptocli/__init__.py
encryptocli/__main__.py
encryptocli/error_handler.py
encryptocli/main.py
encryptocli/encryption/__init__.py
encryptocli/encryption/aes/__init__.py
encryptocli/encryption/aes/cipher.py
encryptocli/encryption/pgp/__init__.py
encryptocli/encryption/pgp/cipher.py
encryptocli/interfaces/__init__.py
encryptocli/interfaces/cli_handler.py
encryptocli/interfaces/tui_handler.py
encryptocli/services/__init__.py
encryptocli/services/decryption_service.py
encryptocli/services/encryption_service.py
encryptocli/services/hashing_service.py
encryptocli/steganography/__init__.py
encryptocli/steganography/dct/__init__.py
encryptocli/steganography/dct/handler.py
encryptocli/steganography/lsb/__init__.py
encryptocli/steganography/lsb/handler.py
encryptocli/util/__init__.py
encryptocli/util/exceptions.py
encryptocli/util/file_handling.py
encryptocli/util/key_gen.py
encryptocli-0.4.0.dist-info/licenses/LICENSE
encryptocli-0.4.0.dist-info/METADATA
encryptocli-0.4.0.dist-info/WHEEL
encryptocli-0.4.0.dist-info/entry_points.txt
encryptocli-0.4.0.dist-info/top_level.txt
encryptocli-0.4.0.dist-info/RECORD
