Metadata-Version: 2.4
Name: EncryptoCLI
Version: 0.4.0
Summary: A command-line program for encrypting, decrypting, and hashing files
Author-email: Arpan Pandey <arpan@example.com>
Maintainer-email: Arpan Pandey <arpan@example.com>
License: MIT
Project-URL: Homepage, https://github.com/Arpan-206/EncryptoCLI
Project-URL: Repository, https://github.com/Arpan-206/EncryptoCLI.git
Project-URL: Documentation, https://arpan-206.github.io/EncryptoCLI/
Project-URL: Issues, https://github.com/Arpan-206/EncryptoCLI/issues
Keywords: encryption,decryption,hashing,steganography,cli,cryptography
Classifier: Development Status :: 3 - Alpha
Classifier: Environment :: Console
Classifier: Intended Audience :: End Users/Desktop
Classifier: Intended Audience :: Developers
Classifier: License :: OSI Approved :: MIT License
Classifier: Operating System :: OS Independent
Classifier: Programming Language :: Python :: 3
Classifier: Programming Language :: Python :: 3.10
Classifier: Programming Language :: Python :: 3.11
Classifier: Programming Language :: Python :: 3.12
Classifier: Programming Language :: Python :: 3.13
Classifier: Topic :: Security :: Cryptography
Classifier: Topic :: System :: Systems Administration
Classifier: Topic :: Utilities
Requires-Python: >=3.10
License-File: LICENSE
Requires-Dist: autopep8
Requires-Dist: blake3
Requires-Dist: cffi
Requires-Dist: colorama
Requires-Dist: crayons
Requires-Dist: cryptography
Requires-Dist: InquirerPy
Requires-Dist: numpy
Requires-Dist: opencv-python
Requires-Dist: piexif
Requires-Dist: Pillow
Requires-Dist: pycodestyle
Requires-Dist: pycparser
Requires-Dist: pyfiglet
Requires-Dist: Pygments
Requires-Dist: python-gnupg
Requires-Dist: regex
Requires-Dist: scipy>=1.15.3
Requires-Dist: six
Requires-Dist: termcolor
Requires-Dist: toml
Requires-Dist: typer>=0.21.1
Requires-Dist: wcwidth
Provides-Extra: docs
Requires-Dist: mkdocs>=1.5.0; extra == "docs"
Requires-Dist: mkdocs-material>=9.5.0; extra == "docs"
Requires-Dist: mkdocstrings[python]>=0.24.0; extra == "docs"
Provides-Extra: test
Requires-Dist: pytest>=7.4.0; extra == "test"
Requires-Dist: pytest-cov>=4.1.0; extra == "test"
Requires-Dist: hypothesis>=6.92.0; extra == "test"
Provides-Extra: dev
Requires-Dist: pytest>=7.4.0; extra == "dev"
Requires-Dist: pytest-cov>=4.1.0; extra == "dev"
Requires-Dist: hypothesis>=6.92.0; extra == "dev"
Requires-Dist: mkdocs>=1.5.0; extra == "dev"
Requires-Dist: mkdocs-material>=9.5.0; extra == "dev"
Requires-Dist: mkdocstrings[python]>=0.24.0; extra == "dev"
Dynamic: license-file
